setup.py
katoun/__init__.py
katoun/main.py
katoun.egg-info/PKG-INFO
katoun.egg-info/SOURCES.txt
katoun.egg-info/dependency_links.txt
katoun.egg-info/entry_points.txt
katoun.egg-info/top_level.txt