Metadata-Version: 1.0
Name: katoun
Version: 1.0.5
Summary: An application to display my beybey katoun in ASCII <3
Home-page: UNKNOWN
Author: Tiffany Souterre
Author-email: UNKNOWN
License: UNKNOWN
Platform: UNKNOWN
